clang_api_doc/__init__.py
clang_api_doc/clang_api_doc.py
clang_api_doc/cli.py
clang_api_doc-0.4.0.dist-info/entry_points.txt
clang_api_doc-0.4.0.dist-info/LICENSE
clang_api_doc-0.4.0.dist-info/WHEEL
clang_api_doc-0.4.0.dist-info/METADATA
clang_api_doc-0.4.0.dist-info/RECORD
